data_hub_call/dataHubCall.py
data_hub_call/dataHubCallBTHub.py
data_hub_call/dataHubCallCityVervePoP.py
data_hub_call/dataHubCallFactory.py
data_hub_call/dataHubCallTriangulum.py
data_hub_call/hypercatCall.py
data_hub_call/requestInfo.py
data_hub_call/requestInfoBTHub.py
data_hub_call/requestInfoBTHubFetch.py
data_hub_call/requestInfoBTHubPost.py
data_hub_call/requestInfoCityVervePoP.py
data_hub_call/requestInfoCityVervePoPFetch.py
data_hub_call/requestInfoFetchFactory.py
data_hub_call/requestInfoFetchList.py
data_hub_call/requestInfoList.py
data_hub_call/requestInfoTriangulum.py
data_hub_call/requestInfoTriangulumFetch.py
data_hub_call/selectedStreamsDirectory.py
data_hub_call/selectedStreamsFiles.py
data_hub_call/selectedStreamsFromDBHubs.py
data_hub_call/selectedStreamsFromFileHubs.py
data_hub_call-0.14.dist-info/LICENSE
data_hub_call-0.14.dist-info/METADATA
data_hub_call-0.14.dist-info/WHEEL
data_hub_call-0.14.dist-info/top_level.txt
data_hub_call-0.14.dist-info/RECORD
