Metadata-Version: 2.1
Name: data-hub-call
Version: 0.14
Summary: Wraps requests and responses for making calls to hub
Home-page: https://github.com/AnnAnnFryingPan/data_hub_call
Author: Ann Gledson
Author-email: anngledson@gmail.com
License: MIT
Platform: UNKNOWN
